senkuu/__init__.py
senkuu/model.py
senkuu/strategies/__init__.py
senkuu/strategies/activations.py
senkuu/strategies/losses.py
senkuu/strategies/metrics.py
senkuu/strategies/optimizers.py
senkuu/structures/__init__.py
senkuu/structures/layers/__init__.py
senkuu/structures/layers/base.py
senkuu/structures/layers/cost.py
senkuu/structures/layers/dense.py
senkuu/structures/layers/input.py
senkuu/utils/__init__.py
senkuu-0.1.0.dist-info/LICENSE
senkuu-0.1.0.dist-info/METADATA
senkuu-0.1.0.dist-info/WHEEL
senkuu-0.1.0.dist-info/top_level.txt
senkuu-0.1.0.dist-info/RECORD
