Metadata-Version: 2.1
Name: senkuu
Version: 0.1.0
Summary: Deep Learning for beginner
Home-page: https://github.com/iqianshuai/senkuu
Author: iqianshuai
Author-email: iqianshuai@163.com
License: UNKNOWN
Platform: UNKNOWN
Classifier: Programming Language :: Python :: 3
Classifier: License :: OSI Approved :: Apache Software License
Classifier: Operating System :: OS Independent
Requires-Python: >=3.6
